datasci_agents/__init__.py
datasci_agents/__main__.py
datasci_agents/cli.py
datasci_agents/experiment.py
datasci_agents/experiment_agent.py
datasci_agents/experiment_factory.py
datasci_agents/experiment_session.py
datasci_agents/llm.py
datasci_agents/project.py
datasci_agents-0.1.0.dist-info/LICENSE
datasci_agents-0.1.0.dist-info/WHEEL
datasci_agents-0.1.0.dist-info/entry_points.txt
datasci_agents-0.1.0.dist-info/METADATA
datasci_agents-0.1.0.dist-info/RECORD
